CHANGELOG.rst
LICENSE
MANIFEST.in
README.rst
requirements.txt
setup.cfg
setup.py
115wangpan.egg-info/PKG-INFO
115wangpan.egg-info/SOURCES.txt
115wangpan.egg-info/dependency_links.txt
115wangpan.egg-info/not-zip-safe
115wangpan.egg-info/requires.txt
115wangpan.egg-info/top_level.txt
bin/115
bin/115down
bin/115up
u115/__init__.py
u115/api.py
u115/conf.py
u115/utils.py