Metadata-Version: 1.1
Name: 115wangpan
Version: 0.7.6
Summary: Unofficial Python API wrapper for 115.com
Home-page: https://github.com/shichao-an/115wangpan
Author: Shichao An
Author-email: shichao.an@nyu.edu
License: BSD
Keywords: 115 wangpan pan cloud lixian
Platform: UNKNOWN
Classifier: License :: OSI Approved :: BSD License
Classifier: Programming Language :: Python
Classifier: Programming Language :: Python :: 2
Classifier: Programming Language :: Python :: 3
